[{"Name": "Courtney Act", "Birth year": "1982", "Nationality": "Australian", "Gender identity": "Genderqueer", "Notable as": "Drag queen, singer, television personality", "isTrans": true, "Char Count": 34628, "genderFeatFreq": {"she": 19, "her": 16, "their": 7, "e": 7, "he": 26, "his": 8, "him": 3, "queer": 2, "feminine": 1, "ve": 3, "woman": 1, "they": 3, "herself": 24, "man": 2, "women": 2, "himself": 3, "male": 1}}, {"Name": "Aja", "Birth year": "1994", "Nationality": "American", "Gender identity": "Genderfluid", "Notable as": "Drag queen, rapper, television personality", "isTrans": true, "Char Count": 1811, "genderFeatFreq": {}}, {"Name": "Travis Alabanza", "Birth year": "1996", "Nationality": "British", "Gender identity": "Gender non-conforming", "Notable as": "Performance artist, poet, writer, LGBTQ rights activist", "isTrans": true, "Char Count": 7863, "genderFeatFreq": {"their": 16, "queer": 5, "they": 11, "trans": 12, "them": 5, "themselves": 1, "feminine": 1, "transgender": 1, "female": 2, "men": 1, "femme": 1}}, {"Name": "Kaitlyn Alexander", "Birth year": "1992", "Nationality": "Canadian", "Gender identity": "Non-binary", "Notable as": "Actor, writer, web series creator and YouTube personality", "isTrans": true, "Char Count": 5270, "genderFeatFreq": {"their": 5, "they": 12, "non-binary": 5, "queer": 3, "them": 1}}, {"Name": "Qween Amor", "Birth year": "1989", "Nationality": "American", "Gender identity": "", "Notable as": "Erotic dancer", "isTrans": true, "Char Count": 1813, "genderFeatFreq": {"her": 1, "their": 1, "e": 1, "themselves": 1, "man": 1}}, {"Name": "Ruth Baldacchino", "Birth year": "1979", "Nationality": "Maltese", "Gender identity": "Non-binary", "Notable as": "LGBT and intersex human rights activist", "isTrans": true, "Char Count": 3542, "genderFeatFreq": {"trans": 4, "women": 1, "they": 4, "queer": 1, "non-binary": 1, "their": 1, "e": 1}}, {"Name": "Meg-John Barker", "Birth year": "1974", "Nationality": "British", "Gender identity": "Plural / non-binary", "Notable as": "Author, speaker, consultant, activist", "isTrans": true, "Char Count": 12273, "genderFeatFreq": {"queer": 8, "non-binary": 5, "they": 7, "their": 5, "them": 2, "themselves": 1, "trans": 4, "e": 2}}, {"Name": "Thomas Baty", "Birth year": "1869", "Nationality": "British", "Gender identity": "Transgender, non-binary", "Notable as": "Lawyer, writer, editor of the feminist gender studies journal *Urania*", "isTrans": true, "Char Count": 11873, "genderFeatFreq": {"transgender": 4, "his": 21, "he": 28, "him": 6, "male": 1, "women": 2, "himself": 1, "non-binary": 1, "trans": 1, "woman": 1, "her": 1, "e": 1, "man": 1}}, {"Name": "Mal Blum", "Birth year": "1988", "Nationality": "American", "Gender identity": "Non-binary", "Notable as": "Musician, Singer", "isTrans": true, "Char Count": 6964, "genderFeatFreq": {"they": 11, "their": 6, "zee": 1, "her": 2, "transgender": 1, "queer": 2, "non-binary": 1, "him": 1, "them": 1, "he": 1}}, {"Name": "Justin Vivian Bond", "Birth year": "1963", "Nationality": "American", "Gender identity": "Transgender", "Notable as": "Singer-songwriter, drag queen", "isTrans": true, "Char Count": 41149, "genderFeatFreq": {"their": 16, "transgender": 2, "women": 1, "them": 4, "male": 3, "trans": 6, "queer": 11, "man": 12, "her": 3, "he": 6, "his": 3, "they": 11, "she": 3, "ve": 1, "woman": 4, "feminine": 1, "e": 1}}, {"Name": "Kate Bornstein", "Birth year": "1948", "Nationality": "American", "Gender identity": "Gender non-conforming", "Notable as": "Author, playwright, performance artist, and gender theorist", "isTrans": true, "Char Count": 8990, "genderFeatFreq": {"woman": 4, "man": 4, "male": 1, "they": 2, "she": 8, "herself": 1, "per": 1, "trans": 2, "women": 6, "men": 4, "them": 1, "hers": 1, "her": 2, "queer": 9, "transgender": 1}}, {"Name": "Pandora Boxx", "Birth year": "1972", "Nationality": "American", "Gender identity": "Genderfluid", "Notable as": "Drag queen, television personality", "isTrans": true, "Char Count": 13948, "genderFeatFreq": {"her": 12, "she": 12, "their": 1, "queer": 1, "herself": 10, "man": 1}}, {"Name": "Rhea Butcher", "Birth year": "1982", "Nationality": "American", "Gender identity": "Non-binary", "Notable as": "Stand up comic, actor", "isTrans": true, "Char Count": 10023, "genderFeatFreq": {"their": 9, "they": 8, "she": 3, "her": 4, "e": 1, "women": 1, "trans": 1}}, {"Name": "Judith Butler", "Birth year": "1956", "Nationality": "American", "Gender identity": "Non-binary", "Notable as": "Philosopher, gender theorist", "isTrans": true, "Char Count": 66409, "genderFeatFreq": {"woman": 4, "women": 14, "feminine": 1, "queer": 18, "they": 51, "their": 45, "she": 2, "them": 7, "male": 5, "female": 5, "men": 2, "masculine": 1, "his": 4, "her": 6, "him": 1, "he": 2, "themselves": 3, "transgender": 3, "non-binary": 1, "vi": 1, "e": 3, "trans": 1, "man": 1}}, {"Name": "Nicky Case", "Birth year": "Unknown", "Nationality": "Canadian", "Gender identity": "Genderqueer and non-binary", "Notable as": "Independent video game developer", "isTrans": true, "Char Count": 3176, "genderFeatFreq": {"vi": 1, "non-binary": 1}}, {"Name": "Cassils", "Birth year": "Unknown", "Nationality": "Canadian", "Gender identity": "Gender non-conforming", "Notable as": "Performance artist", "isTrans": true, "Char Count": 528, "genderFeatFreq": {}}, {"Name": "Violet Chachki", "Birth year": "1992", "Nationality": "American", "Gender identity": "Genderfluid", "Notable as": "Drag queen, model, television personality", "isTrans": true, "Char Count": 17038, "genderFeatFreq": {"their": 10, "they": 8, "his": 3, "them": 5, "male": 1, "female": 1, "herself": 1, "e": 1, "queer": 1, "trans": 2, "her": 1}}, {"Name": "Shea Coule\u00e9", "Birth year": "1989", "Nationality": "American", "Gender identity": "Non-binary", "Notable as": "Drag queen, musician, television personality", "isTrans": true, "Char Count": 39036, "genderFeatFreq": {"she": 11, "her": 15, "they": 31, "their": 18, "themself": 1, "woman": 1, "female": 2, "them": 2, "queer": 4, "themselves": 1, "trans": 4, "women": 4, "transgender": 2, "non-binary": 2, "herself": 4, "e": 1, "his": 1, "ve": 1, "femme": 1}}, {"Name": "Miley Cyrus", "Birth year": "1992", "Nationality": "American", "Gender identity": "Genderfluid", "Notable as": "Singer, songwriter, and actor", "isTrans": true, "Char Count": 105537, "genderFeatFreq": {"her": 234, "female": 6, "she": 176, "he": 4, "they": 7, "his": 9, "him": 4, "their": 26, "men": 2, "herself": 5, "them": 4, "man": 4, "transgender": 3, "themselves": 3, "queer": 2, "women": 6, "ve": 3, "e": 8, "kit": 1, "male": 1, "jem": 1, "ser": 1}}, {"Name": "Adore Delano", "Birth year": "1989", "Nationality": "American", "Gender identity": "Non-binary", "Notable as": "Singer, songwriter, drag queen, television personality", "isTrans": true, "Char Count": 18217, "genderFeatFreq": {"her": 6, "their": 2, "he": 3, "his": 2, "him": 1, "they": 3, "women": 1, "non-binary": 1, "she": 2}}, {"Name": "Cara Delevingne", "Birth year": "1992", "Nationality": "British", "Gender identity": "Genderfluid", "Notable as": "Model and actor", "isTrans": true, "Char Count": 59172, "genderFeatFreq": {"she": 77, "her": 83, "herself": 7, "their": 4, "ve": 4, "his": 7, "female": 2, "women": 2, "they": 1, "he": 5, "e": 6, "xie": 1}}, {"Name": "Asia Kate Dillon", "Birth year": "1984", "Nationality": "American", "Gender identity": "Non-binary", "Notable as": "Actor", "isTrans": true, "Char Count": 10750, "genderFeatFreq": {"their": 9, "non-binary": 17, "they": 15, "them": 4, "queer": 1, "female": 1, "e": 3, "ve": 1}}, {"Name": "Tommy Dorfman", "Birth year": "1992", "Nationality": "American", "Gender identity": "Non-binary", "Notable as": "Actor", "isTrans": true, "Char Count": 3783, "genderFeatFreq": {"they": 3, "their": 1, "queer": 1, "non-binary": 1, "he": 1}}, {"Name": "Rain Dove", "Birth year": "1989", "Nationality": "American", "Gender identity": "Non-binary", "Notable as": "Model, actor, and activist", "isTrans": true, "Char Count": 7541, "genderFeatFreq": {"their": 7, "male": 2, "female": 2, "women": 6, "ve": 2, "they": 14, "she": 1, "he": 1, "man": 3, "themselves": 2, "them": 2, "men": 2, "woman": 2, "queer": 2, "non-binary": 1, "themself": 1, "femme": 1, "masculine": 1}}, {"Name": "Dorian Electra", "Birth year": "1992", "Nationality": "American", "Gender identity": "Genderfluid", "Notable as": "Singer, songwriter, video and performance artist", "isTrans": true, "Char Count": 18323, "genderFeatFreq": {"their": 6, "they": 9, "woman": 6, "queer": 7, "man": 16, "sim": 1, "he": 1}}, {"Name": "Laganja Estranja", "Birth year": "1988", "Nationality": "American", "Gender identity": "Genderfluid", "Notable as": "Drag queen, television personality", "isTrans": true, "Char Count": 23994, "genderFeatFreq": {"she": 11, "her": 19, "they": 2, "their": 5, "queer": 1, "herself": 2, "themselves": 1, "non-binary": 1, "himself": 7, "trans": 1, "transgender": 1}}, {"Name": "Miss Fame", "Birth year": "1985", "Nationality": "American", "Gender identity": "Genderfluid", "Notable as": "Drag queen, makeup artist, model, television personality", "isTrans": true, "Char Count": 12200, "genderFeatFreq": {"her": 10, "male": 1, "they": 3, "she": 5, "their": 1, "themself": 5, "herself": 2}}, {"Name": "Florian-Ayala Fauna", "Birth year": "Unknown", "Nationality": "American", "Gender identity": "Androgyne", "Notable as": "Artist, musician, and music producer", "isTrans": true, "Char Count": 15117, "genderFeatFreq": {"she": 12, "her": 11, "transgender": 2, "their": 1, "they": 1, "his": 1, "ve": 1, "man": 3, "e": 8}}, {"Name": "Tyler Ford", "Birth year": "1990", "Nationality": "American", "Gender identity": "Agender", "Notable as": "Writer, public speaker", "isTrans": true, "Char Count": 5600, "genderFeatFreq": {"transgender": 6, "non-binary": 3, "they": 5, "female": 1, "male": 1, "their": 5, "them": 4, "her": 2, "man": 1, "queer": 5, "trans": 1, "ve": 1}}, {"Name": "Sarah Gailey", "Birth year": "Unknown", "Nationality": "American", "Gender identity": "Non-binary", "Notable as": "Writer", "isTrans": true, "Char Count": 5686, "genderFeatFreq": {"their": 8, "they": 2, "woman": 1, "non-binary": 1, "women": 4, "her": 1}}, {"Name": "Melanie Gillman", "Birth year": "Unknown", "Nationality": "American", "Gender identity": "Non-binary", "Notable as": "Cartoonist", "isTrans": true, "Char Count": 4685, "genderFeatFreq": {"queer": 5, "non-binary": 2, "their": 4, "they": 4, "herself": 1}}, {"Name": "Grimes", "Birth year": "1988", "Nationality": "Canadian", "Gender identity": "Gender neutral", "Notable as": "Musician", "isTrans": true, "Char Count": 1567, "genderFeatFreq": {}}, {"Name": "Angel Haze", "Birth year": "1991", "Nationality": "American", "Gender identity": "Agender", "Notable as": "Rapper and lyricist", "isTrans": true, "Char Count": 14022, "genderFeatFreq": {"her": 21, "his": 2, "she": 18, "man": 1, "they": 6, "them": 2, "themselves": 1, "queer": 1, "their": 8, "woman": 1, "male": 1, "female": 3, "herself": 1, "him": 1, "men": 1, "women": 1, "e": 2}}, {"Name": "Johanna Hedva", "Birth year": "1982", "Nationality": "Korean American", "Gender identity": "Genderqueer", "Notable as": "Artist and author in disability studies", "isTrans": true, "Char Count": 11281, "genderFeatFreq": {"woman": 8, "women": 1, "her": 2, "his": 1, "queer": 2, "they": 2, "their": 5, "she": 1}}, {"Name": "Liv Hewson", "Birth year": "1995", "Nationality": "Australian", "Gender identity": "Non-binary", "Notable as": "Actor and playwright", "isTrans": true, "Char Count": 4460, "genderFeatFreq": {"their": 4, "queer": 1, "they": 4, "them": 1, "non-binary": 2, "ve": 1}}, {"Name": "Lann Hornscheidt", "Birth year": "1965", "Nationality": "German", "Gender identity": "Non-binary", "Notable as": "Academic", "isTrans": true, "Char Count": 4834, "genderFeatFreq": {"non-binary": 1, "male": 1, "female": 1, "sie": 1}}, {"Name": "Jana Hunter", "Birth year": "Unknown", "Nationality": "American", "Gender identity": "Genderfluid", "Notable as": "Songwriter and musician", "isTrans": true, "Char Count": 6232, "genderFeatFreq": {"their": 4, "them": 1, "they": 4, "non-binary": 1, "trans": 1, "female": 1, "woman": 1}}, {"Name": "Eddie Izzard", "Birth year": "1962", "Nationality": "British", "Gender identity": "Transgender", "Notable as": "Comedian, actor and writer", "isTrans": true, "Char Count": 39386, "genderFeatFreq": {"his": 58, "he": 86, "men": 3, "her": 3, "they": 5, "their": 8, "transgender": 6, "him": 2, "himself": 17, "per": 1, "she": 2, "man": 6, "women": 3, "e": 1, "them": 1, "fey": 1}}, {"Name": "Andre J.", "Birth year": "1979", "Nationality": "American", "Gender identity": "Genderless", "Notable as": "Party promoter", "isTrans": true, "Char Count": 4246, "genderFeatFreq": {"they": 18, "their": 7, "transgender": 1, "women": 1, "her": 1, "she": 1, "feminine": 1, "themself": 2, "man": 2, "them": 1, "e": 1, "himself": 2}}, {"Name": "Jesse James Keitel", "Birth year": "Unknown", "Nationality": "American", "Gender identity": "Non-binary", "Notable as": "Actor", "isTrans": true, "Char Count": 4088, "genderFeatFreq": {"they": 4, "e": 3, "their": 1, "queer": 1, "non-binary": 2, "them": 1}}, {"Name": "Janae Kroc", "Birth year": "1972", "Nationality": "American", "Gender identity": "Genderfluid", "Notable as": "Author, bodybuilder, marine, model, pharmacist, powerlifter", "isTrans": true, "Char Count": 16750, "genderFeatFreq": {"male": 6, "man": 3, "transgender": 27, "she": 26, "her": 16, "men": 5, "woman": 5, "they": 4, "female": 4, "he": 6, "his": 5, "e": 1, "ve": 5, "trans": 2, "him": 3, "queer": 1}}, {"Name": "Jiz Lee", "Birth year": "1980", "Nationality": "American", "Gender identity": "Agender", "Notable as": "Pornographic actor", "isTrans": true, "Char Count": 35407, "genderFeatFreq": {"queer": 40, "they": 16, "their": 25, "non-binary": 3, "female": 2, "trans": 10, "women": 6, "e": 5, "masculine": 1, "transgender": 1, "her": 2}}, {"Name": "CN Lester", "Birth year": "1984", "Nationality": "British", "Gender identity": "Genderqueer", "Notable as": "Singer-songwriter", "isTrans": true, "Char Count": 7276, "genderFeatFreq": {"transgender": 1, "they": 9, "their": 14, "queer": 2, "female": 2, "man": 3, "trans": 4, "men": 2, "women": 1, "e": 1}}, {"Name": "Brigette Lundy-Paine", "Birth year": "1994", "Nationality": "American", "Gender identity": "Non-binary", "Notable as": "Actor", "isTrans": true, "Char Count": 3684, "genderFeatFreq": {"their": 3, "they": 1, "non-binary": 5, "man": 1, "them": 1, "her": 1}}, {"Name": "Alex MacFarlane", "Birth year": "Unknown", "Nationality": "Australian", "Gender identity": "Androgynous", "Notable as": "First person known with an 'X' sex marker on passport", "isTrans": true, "Char Count": 3173, "genderFeatFreq": {"their": 1, "male": 1, "female": 1, "man": 1, "woman": 1}}, {"Name": "Gopi Shankar Madurai", "Birth year": "1991", "Nationality": "Indian", "Gender identity": "Genderqueer", "Notable as": "Writer, speaker, politician, equal rights activist, recipient of The \nCommonwealth Award", "isTrans": true, "Char Count": 23619, "genderFeatFreq": {"transgender": 14, "her": 2, "trans": 7, "women": 2, "their": 3, "woman": 3, "non-binary": 3, "ze": 1, "themselves": 1, "them": 2, "queer": 2, "cisgender": 1, "female": 2, "male": 2, "man": 1, "transsexual": 1, "hijra": 1, "two-spirit": 1}}, {"Name": "Kelly Mantle", "Birth year": "1976", "Nationality": "American", "Gender identity": "Genderfluid", "Notable as": "Drag queen, actor, television personality", "isTrans": true, "Char Count": 14102, "genderFeatFreq": {"she": 5, "her": 2, "herself": 4, "transgender": 1, "woman": 2, "man": 1, "himself": 1}}, {"Name": "Jeffrey Marsh", "Birth year": "1977", "Nationality": "American", "Gender identity": "Genderqueer", "Notable as": "Vine and social media activist", "isTrans": true, "Char Count": 10875, "genderFeatFreq": {"they": 8, "their": 10, "man": 1, "queer": 3, "them": 2, "ve": 2, "transgender": 2, "his": 1}}, {"Name": "Rose McGowan", "Birth year": "1973", "Nationality": "American", "Gender identity": "Non-binary", "Notable as": "Actor, model, singer and author", "isTrans": true, "Char Count": 45376, "genderFeatFreq": {"her": 64, "man": 6, "she": 65, "he": 8, "his": 8, "herself": 7, "their": 5, "ve": 2, "men": 13, "they": 8, "women": 9, "woman": 9, "femme": 1, "him": 5, "them": 1, "male": 1, "trans": 3, "female": 1, "e": 6}}, {"Name": "Bethany C. Meyers", "Birth year": "1990", "Nationality": "American", "Gender identity": "Non-binary", "Notable as": "fitness entrepreneur", "isTrans": true, "Char Count": 8516, "genderFeatFreq": {"they": 13, "their": 17, "queer": 3, "men": 1, "women": 1, "non-binary": 1, "his": 1, "them": 1}}, {"Name": "Ezra Miller", "Birth year": "1992", "Nationality": "American", "Gender identity": "Queer, genderfluid", "Notable as": "Actor and singer", "isTrans": true, "Char Count": 17420, "genderFeatFreq": {"them": 5, "their": 3, "man": 4, "queer": 7, "ve": 2, "woman": 2, "they": 8, "his": 1, "he": 1, "e": 1}}, {"Name": "sj Miller", "Birth year": "1970", "Nationality": "American", "Gender identity": "Agender", "Notable as": "Academic and social justice activist", "isTrans": true, "Char Count": 8702, "genderFeatFreq": {"female": 1, "male": 1, "transgender": 2, "e": 2, "queer": 4, "trans": 3}}, {"Name": "Jack Monroe", "Birth year": "1988", "Nationality": "British", "Gender identity": "Non-binary transgender", "Notable as": "Journalist", "isTrans": true, "Char Count": 18463, "genderFeatFreq": {"her": 21, "he": 2, "she": 22, "them": 1, "per": 1, "his": 3, "women": 5, "woman": 4, "non-binary": 5, "trans": 1, "male": 1, "cisgender": 1, "herself": 1, "female": 1, "transgender": 2}}, {"Name": "Jinkx Monsoon", "Birth year": "1987", "Nationality": "American", "Gender identity": "Genderfluid", "Notable as": "Drag queen, television personality", "isTrans": true, "Char Count": 21708, "genderFeatFreq": {"their": 9, "him": 8, "they": 5, "non-binary": 2, "ve": 2, "male": 1, "men": 2, "her": 1, "she": 2, "themself": 17, "em": 1, "e": 1, "man": 1}}, {"Name": "Indya Moore", "Birth year": "1994/1995", "Nationality": "American", "Gender identity": "Non-binary", "Notable as": "Actor, model", "isTrans": true, "Char Count": 11778, "genderFeatFreq": {"they": 10, "transgender": 8, "non-binary": 5, "their": 6, "them": 6, "he": 1, "her": 3, "she": 2, "his": 1, "trans": 8, "woman": 4, "women": 3, "cis": 2, "themself": 1, "femme": 1, "theirs": 1}}, {"Name": "Richard O'Brien", "Birth year": "1942", "Nationality": "British and New Zealand", "Gender identity": "Transgender, Genderqueer", "Notable as": "Writer, actor, television presenter and theatre performer", "isTrans": true, "Char Count": 22679, "genderFeatFreq": {"he": 44, "his": 21, "him": 4, "they": 4, "zee": 2, "their": 2, "trans": 3, "himself": 4, "transgender": 2, "male": 3, "female": 2, "women": 4, "them": 1, "woman": 1, "man": 4, "ve": 1}}, {"Name": "Eureka O'Hara", "Birth year": "1990", "Nationality": "American", "Gender identity": "Genderfluid, Gender-neutral", "Notable as": "Drag queen, television personality", "isTrans": true, "Char Count": 13694, "genderFeatFreq": {"they": 5, "their": 5, "her": 4, "she": 5, "them": 2, "man": 2, "transgender": 1, "woman": 1, "themself": 1, "herself": 10, "non-binary": 1, "his": 2, "trans": 1}}, {"Name": "Pidgeon Pagonis", "Birth year": "1986", "Nationality": "American", "Gender identity": "Non-binary", "Notable as": "Intersex human rights activist", "isTrans": true, "Char Count": 8424, "genderFeatFreq": {"they": 21, "queer": 5, "their": 11, "women": 1, "e": 2}}, {"Name": "A. W. Peet", "Birth year": "Unknown", "Nationality": "New Zealand, Canada", "Gender identity": "Non-binary", "Notable as": "Physicist, string theory and quantum gravity", "isTrans": true, "Char Count": 5048, "genderFeatFreq": {"they": 3, "non-binary": 2, "transgender": 1}}, {"Name": "Planningtorock", "Birth year": "", "Nationality": "British", "Gender identity": "Genderqueer", "Notable as": "Musician", "isTrans": true, "Char Count": 8729, "genderFeatFreq": {"their": 7, "they": 6, "he": 1, "them": 3, "his": 1, "non-binary": 1, "she": 3, "queer": 1}}, {"Name": "Chris Pureka", "Birth year": "1979", "Nationality": "American", "Gender identity": "Genderqueer", "Notable as": "Singer-songwriter", "isTrans": true, "Char Count": 7601, "genderFeatFreq": {"their": 11, "they": 15, "her": 2, "e": 1, "female": 1, "queer": 1}}, {"Name": "Bob the Drag Queen", "Birth year": "1986", "Nationality": "American", "Gender identity": "Non-binary", "Notable as": "Drag queen, comedian", "isTrans": true, "Char Count": 23170, "genderFeatFreq": {"their": 2, "she": 7, "he": 20, "his": 13, "him": 2, "kit": 1, "them": 1, "they": 3, "herself": 8, "her": 1, "woman": 3, "queer": 1, "non-binary": 1, "himself": 9, "e": 3}}, {"Name": "L.J. Roberts", "Birth year": "1980", "Nationality": "American", "Gender identity": "Genderqueer", "Notable as": "Textile artist", "isTrans": true, "Char Count": 7629, "genderFeatFreq": {"queer": 16, "they": 11, "their": 14, "them": 1, "non-binary": 1, "e": 3}}, {"Name": "Megan Rohrer", "Birth year": "1980", "Nationality": "American", "Gender identity": "Transgender", "Notable as": "Pastor and activist", "isTrans": true, "Char Count": 6831, "genderFeatFreq": {"they": 5, "transgender": 10, "their": 3, "trans": 6, "woman": 2, "male": 1, "e": 3}}, {"Name": "Ruby Rose", "Birth year": "1986", "Nationality": "Australian", "Gender identity": "Genderfluid", "Notable as": "Model, actor, singer and television presenter", "isTrans": true, "Char Count": 32117, "genderFeatFreq": {"she": 82, "her": 43, "their": 8, "they": 9, "female": 4, "herself": 18, "ve": 1, "women": 8, "male": 4, "feminine": 2, "woman": 8, "man": 1, "transgender": 1, "theirs": 1, "trans": 2, "them": 1, "yo": 1, "e": 2}}, {"Name": "Shamir", "Birth year": "1994", "Nationality": "American", "Gender identity": "Non-binary", "Notable as": "Singer-songwriter", "isTrans": true, "Char Count": 895, "genderFeatFreq": {}}, {"Name": "SMITH", "Birth year": "1985", "Nationality": "French", "Gender identity": "", "Notable as": "Artist and film-maker", "isTrans": true, "Char Count": 4513, "genderFeatFreq": {"they": 1, "their": 2}}, {"Name": "Sam Smith", "Birth year": "1992", "Nationality": "British", "Gender identity": "Non-binary and genderqueer", "Notable as": "Singer", "isTrans": true, "Char Count": 53696, "genderFeatFreq": {"their": 27, "non-binary": 2, "they": 19, "ve": 9, "his": 5, "male": 4, "man": 10, "themself": 1, "him": 2, "woman": 3, "she": 1, "he": 1, "her": 1, "e": 2, "queer": 1, "men": 1}}, {"Name": "Joey Soloway", "Birth year": "1965", "Nationality": "American", "Gender identity": "Non-binary, gender non-conforming", "Notable as": "Writer, director, producer", "isTrans": true, "Char Count": 27935, "genderFeatFreq": {"they": 8, "transgender": 8, "their": 5, "female": 12, "she": 9, "her": 12, "woman": 8, "ve": 2, "women": 9, "them": 1, "male": 4, "feminine": 1, "man": 2, "e": 1, "trans": 2}}, {"Name": "Rae Spoon", "Birth year": "1982", "Nationality": "Canadian", "Gender identity": "", "Notable as": "Musician and writer", "isTrans": true, "Char Count": 9534, "genderFeatFreq": {"their": 7, "transgender": 7, "they": 14, "trans": 2, "man": 2, "non-binary": 3, "he": 2, "woman": 1, "them": 3, "his": 1, "queer": 1, "e": 3}}, {"Name": "Amandla Stenberg", "Birth year": "1998", "Nationality": "American", "Gender identity": "Non-binary", "Notable as": "Actor", "isTrans": true, "Char Count": 20974, "genderFeatFreq": {"her": 29, "she": 40, "woman": 2, "women": 3, "herself": 2, "non-binary": 1, "female": 3, "kit": 1, "male": 1}}, {"Name": "Noelle Stevenson", "Birth year": "1991", "Nationality": "United States", "Gender identity": "Non-binary", "Notable as": "Creator of *She-Ra and the Princesses of Power* and *Nimona*, writer, and \nanimator who is married to Molly Ostertag.", "isTrans": true, "Char Count": 15500, "genderFeatFreq": {"she": 11, "them": 1, "her": 16, "his": 1, "non-binary": 1, "woman": 1, "hers": 1}}, {"Name": "Rebecca Sugar", "Birth year": "1987", "Nationality": "American", "Gender identity": "Non-binary", "Notable as": "Animator, director, screenwriter, producer, and songwriter", "isTrans": true, "Char Count": 16403, "genderFeatFreq": {"she": 24, "her": 19, "woman": 5, "non-binary": 6, "them": 2, "he": 3, "their": 2, "they": 3, "women": 1, "herself": 2, "his": 1, "queer": 1, "ve": 1, "female": 1}}, {"Name": "Tanwarin Sukkhapisit", "Birth year": "", "Nationality": "Thai", "Gender identity": "Non-binary", "Notable as": "Filmmaker, politician", "isTrans": true, "Char Count": 2125, "genderFeatFreq": {"transgender": 6, "her": 2, "she": 1}}, {"Name": "Emma Sulkowicz", "Birth year": "1992", "Nationality": "American", "Gender identity": "Non-binary", "Notable as": "Performance artist, anti-rape activist", "isTrans": true, "Char Count": 17439, "genderFeatFreq": {"she": 14, "her": 19, "non-binary": 1, "he": 2, "they": 3, "herself": 3, "man": 2, "themselves": 1, "ve": 1, "their": 2, "them": 1, "woman": 2, "cis": 1, "men": 1, "his": 3, "women": 2}}, {"Name": "Eliot Sumner", "Birth year": "1990", "Nationality": "British", "Gender identity": "Genderfluid", "Notable as": "Musician, singer-songwriter", "isTrans": true, "Char Count": 11741, "genderFeatFreq": {"he": 1, "their": 5, "they": 10, "her": 1, "man": 1, "them": 1}}, {"Name": "Mattilda Bernstein Sycamore", "Birth year": "1973", "Nationality": "American", "Gender identity": "Genderqueer", "Notable as": "Author and activist", "isTrans": true, "Char Count": 11301, "genderFeatFreq": {"she": 8, "their": 3, "her": 10, "queer": 19, "e": 3, "trans": 4, "transgender": 2, "herself": 1}}, {"Name": "Bex Taylor-Klaus", "Birth year": "1994", "Nationality": "American", "Gender identity": "Non-binary", "Notable as": "Actor", "isTrans": true, "Char Count": 11095, "genderFeatFreq": {"they": 14, "their": 8, "non-binary": 2, "themself": 1, "trans": 2, "transgender": 1, "e": 1, "ve": 1, "woman": 1}}, {"Name": "Kae Tempest", "Birth year": "1985", "Nationality": "British", "Gender identity": "Non-binary", "Notable as": "Poet", "isTrans": true, "Char Count": 14508, "genderFeatFreq": {"them": 13, "they": 22, "their": 23, "female": 5, "non-binary": 2, "him": 2, "man": 1}}, {"Name": "T. Thomason", "Birth year": "1994", "Nationality": "Canadian", "Gender identity": "Non-binary", "Notable as": "Singer-songwriter", "isTrans": true, "Char Count": 6192, "genderFeatFreq": {"their": 11, "non-binary": 1, "they": 3, "she": 2, "his": 1, "her": 2, "transgender": 1}}, {"Name": "JayR Tinaco", "Birth year": "1989", "Nationality": "Australian", "Gender identity": "Non-binary", "Notable as": "actor", "isTrans": true, "Char Count": 3109, "genderFeatFreq": {"their": 4, "they": 1, "non-binary": 3, "them": 1}}, {"Name": "Jacob Tobia", "Birth year": "1991", "Nationality": "American", "Gender identity": "Genderqueer", "Notable as": "Writer and activist", "isTrans": true, "Char Count": 12443, "genderFeatFreq": {"they": 15, "their": 5, "ve": 1, "queer": 5, "non-binary": 3, "transgender": 2, "trans": 10, "women": 4}}, {"Name": "Nico Tortorella", "Birth year": "1988", "Nationality": "American", "Gender identity": "Gender fluid", "Notable as": "Actor and model", "isTrans": true, "Char Count": 8332, "genderFeatFreq": {"they": 9, "their": 3, "themself": 6, "them": 2, "man": 2, "his": 1, "he": 1, "e": 1}}, {"Name": "Mauree Turner", "Birth year": "", "Nationality": "American", "Gender identity": "Non-binary", "Notable as": "Politician", "isTrans": true, "Char Count": 4341, "genderFeatFreq": {"they": 7, "non-binary": 4, "themself": 1, "their": 2, "queer": 1, "trans": 1}}, {"Name": "Alok Vaid-Menon", "Birth year": "1991", "Nationality": "American", "Gender identity": "Non-binary", "Notable as": "Spoken word performance", "isTrans": true, "Char Count": 14852, "genderFeatFreq": {"they": 36, "their": 16, "trans": 7, "themself": 2, "femme": 7, "transgender": 4, "queer": 4, "man": 1}}, {"Name": "Jonathan Van Ness", "Birth year": "1987", "Nationality": "American", "Gender identity": "Non-binary, genderqueer", "Notable as": "Hairdresser, podcaster, television personality", "isTrans": true, "Char Count": 26317, "genderFeatFreq": {"his": 26, "he": 32, "queer": 28, "non-binary": 2, "their": 2, "men": 2, "male": 2, "they": 6, "themselves": 2, "them": 3, "himself": 30, "e": 5, "she": 3, "her": 3, "woman": 3, "trans": 1, "ve": 2, "him": 1, "herself": 1}}, {"Name": "Joanne Vannicola", "Birth year": "1968", "Nationality": "Canadian", "Gender identity": "Non-binary", "Notable as": "Actor, writer", "isTrans": true, "Char Count": 8922, "genderFeatFreq": {"they": 8, "their": 7, "non-binary": 3, "men": 1, "female": 1, "her": 2}}, {"Name": "Sasha Velour", "Birth year": "1987", "Nationality": "American", "Gender identity": "Non-binary", "Notable as": "Drag queen, television personality", "isTrans": true, "Char Count": 16275, "genderFeatFreq": {"her": 12, "she": 9, "their": 1, "queer": 3, "herself": 8, "ve": 1}}, {"Name": "Hida Viloria", "Birth year": "1968", "Nationality": "American", "Gender identity": "Genderfluid", "Notable as": "Author, and LGBT and intersex human rights activist", "isTrans": true, "Char Count": 22808, "genderFeatFreq": {"non-binary": 8, "women": 16, "her": 5, "female": 10, "hers": 1, "she": 10, "herself": 1, "they": 2, "them": 1, "their": 4, "male": 1, "men": 1, "queer": 1, "trans": 1, "cisgender": 1, "man": 1, "woman": 1}}, {"Name": "Lachlan Watson", "Birth year": "2001", "Nationality": "American", "Gender identity": "Genderqueer", "Notable as": "Actor", "isTrans": true, "Char Count": 4945, "genderFeatFreq": {"their": 9, "non-binary": 4, "they": 9, "transgender": 1, "female": 1, "e": 1}}, {"Name": "Karekin Yarian", "Birth year": "Unknown", "Nationality": "American", "Gender identity": "Non-binary", "Notable as": "Author and activist", "isTrans": true, "Char Count": 7258, "genderFeatFreq": {"transgender": 4, "she": 6, "her": 4, "feminine": 1, "non-binary": 1, "women": 1}}, {"Name": "Reuben Zellman", "Birth year": "1979", "Nationality": "American", "Gender identity": "Non-binary", "Notable as": "Rabbi and musician", "isTrans": true, "Char Count": 3951, "genderFeatFreq": {"he": 11, "transgender": 7, "his": 2, "women": 1, "men": 1, "male": 1, "female": 1, "masculine": 1, "non-binary": 1, "e": 1}}, {"Name": "Dana Zzyym", "Birth year": "1958", "Nationality": "American", "Gender identity": "Non-binary", "Notable as": "Intersex human rights activist", "isTrans": true, "Char Count": 2660, "genderFeatFreq": {"non-binary": 2, "their": 5, "them": 3, "queer": 1, "themselves": 1}}, {"Name": "Nevo Zisin", "Birth year": "1996", "Nationality": "Australian", "Gender identity": "Non-binary", "Notable as": "Writer and activist", "isTrans": true, "Char Count": 3345, "genderFeatFreq": {"transgender": 5, "non-binary": 4, "female": 2, "queer": 1, "male": 2, "they": 4, "their": 1, "men": 1}}, {"Name": "Gigi Goode", "Birth year": "1997/1998", "Nationality": "American", "Gender identity": "Genderfluid", "Notable as": "Drag queen, television personality", "isTrans": true, "Char Count": 16364, "genderFeatFreq": {"their": 8, "they": 6, "her": 6, "she": 11, "queer": 2, "herself": 3, "non-binary": 1, "them": 1, "se": 1, "e": 1, "trans": 1}}, {"Name": "King Princess", "Birth year": "1998", "Nationality": "American", "Gender identity": "Genderqueer", "Notable as": "Musician, singer-songwriter", "isTrans": true, "Char Count": 17574, "genderFeatFreq": {"her": 24, "she": 20, "they": 3, "his": 2, "queer": 6, "their": 1, "herself": 2, "woman": 2, "femme": 1, "per": 1, "ve": 1, "them": 1, "women": 1}}, {"Name": "Victoria Sin", "Birth year": "1991", "Nationality": "Canadian", "Gender identity": "Non-binary", "Notable as": "Visual artist, drag performer", "isTrans": true, "Char Count": 5434, "genderFeatFreq": {"they": 6, "their": 9, "male": 1, "queer": 2, "non-binary": 1, "women": 1, "female": 1}}]